{
  "LotNo": 1,
  "TradeObjectList": [
    {
      "LotNo": 1,
      "TradeNoOnThisLot": 1,
      "TradeTime": "22-02-2026 05:08:58",
      "asset": "1HZ75V",
      "action": "call",
      "moneyTrade": 1.0,
      "MoneyTradeType": "Fixed",
      "WinStatus": "loss",
      "Profit": -1.0,
      "BalanceOnLot": -1.0,
      "winCon": "5",
      "lossCon": "10",
      "isstopTrade": false
    },
    {
      "LotNo": 1,
      "TradeNoOnThisLot": 2,
      "TradeTime": "22-02-2026 05:09:02",
      "asset": "R_100",
      "action": "put",
      "moneyTrade": 1.0,
      "MoneyTradeType": "Fixed",
      "WinStatus": "win",
      "Profit": 0.94,
      "BalanceOnLot": -0.06000000000000005,
      "winCon": "5",
      "lossCon": "10",
      "isstopTrade": false
    },
    {
      "LotNo": 1,
      "TradeNoOnThisLot": 3,
      "TradeTime": "22-02-2026 05:09:03",
      "asset": "1HZ25V",
      "action": "call",
      "moneyTrade": 1.0,
      "MoneyTradeType": "Fixed",
      "WinStatus": "win",
      "Profit": 0.95,
      "BalanceOnLot": 0.8899999999999999,
      "winCon": "5",
      "lossCon": "10",
      "isstopTrade": false
    },
    {
      "LotNo": 1,
      "TradeNoOnThisLot": 4,
      "TradeTime": "22-02-2026 05:10:01",
      "asset": "1HZ25V",
      "action": "call",
      "moneyTrade": 1.0,
      "MoneyTradeType": "Fixed",
      "WinStatus": "win",
      "Profit": 0.95,
      "BalanceOnLot": 1.8399999999999999,
      "winCon": "5",
      "lossCon": "10",
      "isstopTrade": false
    },
    {
      "LotNo": 1,
      "TradeNoOnThisLot": 5,
      "TradeTime": "22-02-2026 05:10:01",
      "asset": "1HZ50V",
      "action": "put",
      "moneyTrade": 1.0,
      "MoneyTradeType": "Fixed",
      "WinStatus": "loss",
      "Profit": -1.0,
      "BalanceOnLot": 0.8399999999999999,
      "winCon": "5",
      "lossCon": "10",
      "isstopTrade": false
    },
    {
      "LotNo": 1,
      "TradeNoOnThisLot": 6,
      "TradeTime": "22-02-2026 05:10:02",
      "asset": "1HZ75V",
      "action": "put",
      "moneyTrade": 1.0,
      "MoneyTradeType": "Fixed",
      "WinStatus": "win",
      "Profit": 0.94,
      "BalanceOnLot": 1.7799999999999998,
      "winCon": "5",
      "lossCon": "10",
      "isstopTrade": false
    },
    {
      "LotNo": 1,
      "TradeNoOnThisLot": 7,
      "TradeTime": "22-02-2026 05:10:02",
      "asset": "R_25",
      "action": "put",
      "moneyTrade": 1.0,
      "MoneyTradeType": "Fixed",
      "WinStatus": "loss",
      "Profit": -1.0,
      "BalanceOnLot": 0.7799999999999998,
      "winCon": "5",
      "lossCon": "10",
      "isstopTrade": false
    },
    {
      "LotNo": 1,
      "TradeNoOnThisLot": 8,
      "TradeTime": "22-02-2026 05:10:58",
      "asset": "1HZ75V",
      "action": "put",
      "moneyTrade": 1.0,
      "MoneyTradeType": "Fixed",
      "WinStatus": "loss",
      "Profit": -1.0,
      "BalanceOnLot": -0.2200000000000002,
      "winCon": "5",
      "lossCon": "10",
      "isstopTrade": false
    },
    {
      "LotNo": 1,
      "TradeNoOnThisLot": 9,
      "TradeTime": "22-02-2026 05:10:58",
      "asset": "R_100",
      "action": "put",
      "moneyTrade": 1.0,
      "MoneyTradeType": "Fixed",
      "WinStatus": "loss",
      "Profit": -1.0,
      "BalanceOnLot": -1.2200000000000002,
      "winCon": "5",
      "lossCon": "10",
      "isstopTrade": false
    },
    {
      "LotNo": 1,
      "TradeNoOnThisLot": 10,
      "TradeTime": "22-02-2026 05:10:58",
      "asset": "1HZ50V",
      "action": "put",
      "moneyTrade": 1.0,
      "MoneyTradeType": "Fixed",
      "WinStatus": "loss",
      "Profit": -1.0,
      "BalanceOnLot": -2.22,
      "winCon": "5",
      "lossCon": "10",
      "isstopTrade": false
    },
    {
      "LotNo": 1,
      "TradeNoOnThisLot": 11,
      "TradeTime": "22-02-2026 05:11:58",
      "asset": "R_75",
      "action": "call",
      "moneyTrade": 1.0,
      "MoneyTradeType": "Fixed",
      "WinStatus": "win",
      "Profit": 0.95,
      "BalanceOnLot": -1.2700000000000002,
      "winCon": "5",
      "lossCon": "10",
      "isstopTrade": false
    },
    {
      "LotNo": 1,
      "TradeNoOnThisLot": 12,
      "TradeTime": "22-02-2026 05:11:58",
      "asset": "R_100",
      "action": "put",
      "moneyTrade": 1.0,
      "MoneyTradeType": "Fixed",
      "WinStatus": "loss",
      "Profit": -1.0,
      "BalanceOnLot": -2.2700000000000005,
      "winCon": "5",
      "lossCon": "10",
      "isstopTrade": false
    },
    {
      "LotNo": 1,
      "TradeNoOnThisLot": 13,
      "TradeTime": "22-02-2026 05:11:58",
      "asset": "1HZ100V",
      "action": "put",
      "moneyTrade": 1.0,
      "MoneyTradeType": "Fixed",
      "WinStatus": "win",
      "Profit": 0.94,
      "BalanceOnLot": -1.3300000000000005,
      "winCon": "5",
      "lossCon": "10",
      "isstopTrade": false
    },
    {
      "LotNo": 1,
      "TradeNoOnThisLot": 14,
      "TradeTime": "22-02-2026 05:12:58",
      "asset": "R_25",
      "action": "put",
      "moneyTrade": 1.0,
      "MoneyTradeType": "Fixed",
      "WinStatus": "win",
      "Profit": 0.95,
      "BalanceOnLot": -0.38000000000000056,
      "winCon": "5",
      "lossCon": "10",
      "isstopTrade": false
    },
    {
      "LotNo": 1,
      "TradeNoOnThisLot": 15,
      "TradeTime": "22-02-2026 05:13:01",
      "asset": "R_50",
      "action": "put",
      "moneyTrade": 1.0,
      "MoneyTradeType": "Fixed",
      "WinStatus": "win",
      "Profit": 0.95,
      "BalanceOnLot": 0.5699999999999994,
      "winCon": "5",
      "lossCon": "10",
      "isstopTrade": false
    },
    {
      "LotNo": 1,
      "TradeNoOnThisLot": 16,
      "TradeTime": "22-02-2026 05:13:01",
      "asset": "R_75",
      "action": "call",
      "moneyTrade": 1.0,
      "MoneyTradeType": "Fixed",
      "WinStatus": "win",
      "Profit": 0.95,
      "BalanceOnLot": 1.5199999999999994,
      "winCon": "5",
      "lossCon": "10",
      "isstopTrade": false
    },
    {
      "LotNo": 1,
      "TradeNoOnThisLot": 17,
      "TradeTime": "22-02-2026 05:13:57",
      "asset": "1HZ10V",
      "action": "call",
      "moneyTrade": 1.0,
      "MoneyTradeType": "Fixed",
      "WinStatus": "win",
      "Profit": 0.95,
      "BalanceOnLot": 2.4699999999999993,
      "winCon": "5",
      "lossCon": "10",
      "isstopTrade": false
    },
    {
      "LotNo": 1,
      "TradeNoOnThisLot": 18,
      "TradeTime": "22-02-2026 05:14:04",
      "asset": "R_75",
      "action": "call",
      "moneyTrade": 1.0,
      "MoneyTradeType": "Fixed",
      "WinStatus": "loss",
      "Profit": -1.0,
      "BalanceOnLot": 1.4699999999999993,
      "winCon": "5",
      "lossCon": "10",
      "isstopTrade": false
    },
    {
      "LotNo": 1,
      "TradeNoOnThisLot": 19,
      "TradeTime": "22-02-2026 05:15:03",
      "asset": "1HZ10V",
      "action": "call",
      "moneyTrade": 1.0,
      "MoneyTradeType": "Fixed",
      "WinStatus": "win",
      "Profit": 0.95,
      "BalanceOnLot": 2.419999999999999,
      "winCon": "5",
      "lossCon": "10",
      "isstopTrade": false
    },
    {
      "LotNo": 1,
      "TradeNoOnThisLot": 20,
      "TradeTime": "22-02-2026 05:15:05",
      "asset": "R_50",
      "action": "put",
      "moneyTrade": 1.0,
      "MoneyTradeType": "Fixed",
      "WinStatus": "loss",
      "Profit": -1.0,
      "BalanceOnLot": 1.419999999999999,
      "winCon": "5",
      "lossCon": "10",
      "isstopTrade": false
    },
    {
      "LotNo": 1,
      "TradeNoOnThisLot": 21,
      "TradeTime": "22-02-2026 05:15:05",
      "asset": "R_75",
      "action": "call",
      "moneyTrade": 1.0,
      "MoneyTradeType": "Fixed",
      "WinStatus": "loss",
      "Profit": -1.0,
      "BalanceOnLot": 0.41999999999999904,
      "winCon": "5",
      "lossCon": "10",
      "isstopTrade": false
    },
    {
      "LotNo": 1,
      "TradeNoOnThisLot": 22,
      "TradeTime": "22-02-2026 05:15:05",
      "asset": "R_100",
      "action": "put",
      "moneyTrade": 1.0,
      "MoneyTradeType": "Fixed",
      "WinStatus": "win",
      "Profit": 0.94,
      "BalanceOnLot": 1.359999999999999,
      "winCon": "5",
      "lossCon": "10",
      "isstopTrade": false
    },
    {
      "LotNo": 1,
      "TradeNoOnThisLot": 23,
      "TradeTime": "22-02-2026 05:15:05",
      "asset": "R_25",
      "action": "put",
      "moneyTrade": 1.0,
      "MoneyTradeType": "Fixed",
      "WinStatus": "loss",
      "Profit": -1.0,
      "BalanceOnLot": 0.359999999999999,
      "winCon": "5",
      "lossCon": "10",
      "isstopTrade": false
    },
    {
      "LotNo": 1,
      "TradeNoOnThisLot": 24,
      "TradeTime": "22-02-2026 05:15:58",
      "asset": "R_25",
      "action": "put",
      "moneyTrade": 1.0,
      "MoneyTradeType": "Fixed",
      "WinStatus": "win",
      "Profit": 0.95,
      "BalanceOnLot": 1.309999999999999,
      "winCon": "5",
      "lossCon": "10",
      "isstopTrade": false
    },
    {
      "LotNo": 1,
      "TradeNoOnThisLot": 25,
      "TradeTime": "22-02-2026 05:15:59",
      "asset": "1HZ75V",
      "action": "put",
      "moneyTrade": 1.0,
      "MoneyTradeType": "Fixed",
      "WinStatus": "win",
      "Profit": 0.94,
      "BalanceOnLot": 2.249999999999999,
      "winCon": "5",
      "lossCon": "10",
      "isstopTrade": false
    },
    {
      "LotNo": 1,
      "TradeNoOnThisLot": 26,
      "TradeTime": "22-02-2026 05:15:59",
      "asset": "1HZ10V",
      "action": "call",
      "moneyTrade": 1.0,
      "MoneyTradeType": "Fixed",
      "WinStatus": "loss",
      "Profit": -1.0,
      "BalanceOnLot": 1.2499999999999991,
      "winCon": "5",
      "lossCon": "10",
      "isstopTrade": false
    },
    {
      "LotNo": 1,
      "TradeNoOnThisLot": 27,
      "TradeTime": "22-02-2026 05:15:59",
      "asset": "1HZ100V",
      "action": "put",
      "moneyTrade": 1.0,
      "MoneyTradeType": "Fixed",
      "WinStatus": "loss",
      "Profit": -1.0,
      "BalanceOnLot": 0.2499999999999991,
      "winCon": "5",
      "lossCon": "10",
      "isstopTrade": false
    },
    {
      "LotNo": 1,
      "TradeNoOnThisLot": 28,
      "TradeTime": "22-02-2026 05:16:02",
      "asset": "R_100",
      "action": "put",
      "moneyTrade": 1.0,
      "MoneyTradeType": "Fixed",
      "WinStatus": "win",
      "Profit": 0.94,
      "BalanceOnLot": 1.189999999999999,
      "winCon": "5",
      "lossCon": "10",
      "isstopTrade": false
    },
    {
      "LotNo": 1,
      "TradeNoOnThisLot": 29,
      "TradeTime": "22-02-2026 05:16:58",
      "asset": "1HZ50V",
      "action": "put",
      "moneyTrade": 1.0,
      "MoneyTradeType": "Fixed",
      "WinStatus": "win",
      "Profit": 0.95,
      "BalanceOnLot": 2.139999999999999,
      "winCon": "5",
      "lossCon": "10",
      "isstopTrade": false
    },
    {
      "LotNo": 1,
      "TradeNoOnThisLot": 30,
      "TradeTime": "22-02-2026 05:16:59",
      "asset": "1HZ10V",
      "action": "call",
      "moneyTrade": 1.0,
      "MoneyTradeType": "Fixed",
      "WinStatus": "win",
      "Profit": 0.95,
      "BalanceOnLot": 3.089999999999999,
      "winCon": "5",
      "lossCon": "10",
      "isstopTrade": false
    },
    {
      "LotNo": 1,
      "TradeNoOnThisLot": 31,
      "TradeTime": "22-02-2026 05:16:59",
      "asset": "1HZ75V",
      "action": "put",
      "moneyTrade": 1.0,
      "MoneyTradeType": "Fixed",
      "WinStatus": "win",
      "Profit": 0.94,
      "BalanceOnLot": 4.029999999999999,
      "winCon": "5",
      "lossCon": "10",
      "isstopTrade": false
    },
    {
      "LotNo": 1,
      "TradeNoOnThisLot": 32,
      "TradeTime": "22-02-2026 05:16:59",
      "asset": "R_100",
      "action": "put",
      "moneyTrade": 1.0,
      "MoneyTradeType": "Fixed",
      "WinStatus": "loss",
      "Profit": -1.0,
      "BalanceOnLot": 3.0299999999999994,
      "winCon": "5",
      "lossCon": "10",
      "isstopTrade": false
    },
    {
      "LotNo": 1,
      "TradeNoOnThisLot": 33,
      "TradeTime": "22-02-2026 05:16:59",
      "asset": "1HZ100V",
      "action": "put",
      "moneyTrade": 1.0,
      "MoneyTradeType": "Fixed",
      "WinStatus": "win",
      "Profit": 0.94,
      "BalanceOnLot": 3.9699999999999993,
      "winCon": "5",
      "lossCon": "10",
      "isstopTrade": false
    },
    {
      "LotNo": 1,
      "TradeNoOnThisLot": 34,
      "TradeTime": "22-02-2026 05:17:02",
      "asset": "R_50",
      "action": "put",
      "moneyTrade": 1.0,
      "MoneyTradeType": "Fixed",
      "WinStatus": "loss",
      "Profit": -1.0,
      "BalanceOnLot": 2.9699999999999993,
      "winCon": "5",
      "lossCon": "10",
      "isstopTrade": false
    },
    {
      "LotNo": 1,
      "TradeNoOnThisLot": 35,
      "TradeTime": "22-02-2026 05:17:58",
      "asset": "R_75",
      "action": "call",
      "moneyTrade": 1.0,
      "MoneyTradeType": "Fixed",
      "WinStatus": "loss",
      "Profit": -1.0,
      "BalanceOnLot": 1.9699999999999993,
      "winCon": "5",
      "lossCon": "10",
      "isstopTrade": false
    },
    {
      "LotNo": 1,
      "TradeNoOnThisLot": 36,
      "TradeTime": "22-02-2026 05:17:58",
      "asset": "R_25",
      "action": "put",
      "moneyTrade": 1.0,
      "MoneyTradeType": "Fixed",
      "WinStatus": "loss",
      "Profit": -1.0,
      "BalanceOnLot": 0.9699999999999993,
      "winCon": "5",
      "lossCon": "10",
      "isstopTrade": false
    },
    {
      "LotNo": 1,
      "TradeNoOnThisLot": 37,
      "TradeTime": "22-02-2026 05:17:58",
      "asset": "1HZ50V",
      "action": "put",
      "moneyTrade": 1.0,
      "MoneyTradeType": "Fixed",
      "WinStatus": "loss",
      "Profit": -1.0,
      "BalanceOnLot": -0.030000000000000693,
      "winCon": "5",
      "lossCon": "10",
      "isstopTrade": false
    },
    {
      "LotNo": 1,
      "TradeNoOnThisLot": 38,
      "TradeTime": "22-02-2026 05:17:59",
      "asset": "1HZ10V",
      "action": "call",
      "moneyTrade": 1.0,
      "MoneyTradeType": "Fixed",
      "WinStatus": "win",
      "Profit": 0.95,
      "BalanceOnLot": 0.9199999999999993,
      "winCon": "5",
      "lossCon": "10",
      "isstopTrade": false
    },
    {
      "LotNo": 1,
      "TradeNoOnThisLot": 39,
      "TradeTime": "22-02-2026 05:17:59",
      "asset": "1HZ75V",
      "action": "put",
      "moneyTrade": 1.0,
      "MoneyTradeType": "Fixed",
      "WinStatus": "loss",
      "Profit": -1.0,
      "BalanceOnLot": -0.08000000000000074,
      "winCon": "5",
      "lossCon": "10",
      "isstopTrade": false
    },
    {
      "LotNo": 1,
      "TradeNoOnThisLot": 40,
      "TradeTime": "22-02-2026 05:18:02",
      "asset": "R_100",
      "action": "put",
      "moneyTrade": 1.0,
      "MoneyTradeType": "Fixed",
      "WinStatus": "win",
      "Profit": 0.94,
      "BalanceOnLot": 0.8599999999999992,
      "winCon": "5",
      "lossCon": "10",
      "isstopTrade": false
    },
    {
      "LotNo": 1,
      "TradeNoOnThisLot": 41,
      "TradeTime": "22-02-2026 05:18:58",
      "asset": "R_75",
      "action": "call",
      "moneyTrade": 1.0,
      "MoneyTradeType": "Fixed",
      "WinStatus": "loss",
      "Profit": -1.0,
      "BalanceOnLot": -0.1400000000000008,
      "winCon": "5",
      "lossCon": "10",
      "isstopTrade": false
    },
    {
      "LotNo": 1,
      "TradeNoOnThisLot": 42,
      "TradeTime": "22-02-2026 05:18:59",
      "asset": "R_25",
      "action": "put",
      "moneyTrade": 1.0,
      "MoneyTradeType": "Fixed",
      "WinStatus": "win",
      "Profit": 0.95,
      "BalanceOnLot": 0.8099999999999992,
      "winCon": "5",
      "lossCon": "10",
      "isstopTrade": false
    },
    {
      "LotNo": 1,
      "TradeNoOnThisLot": 43,
      "TradeTime": "22-02-2026 05:18:59",
      "asset": "1HZ50V",
      "action": "put",
      "moneyTrade": 1.0,
      "MoneyTradeType": "Fixed",
      "WinStatus": "win",
      "Profit": 0.95,
      "BalanceOnLot": 1.7599999999999991,
      "winCon": "5",
      "lossCon": "10",
      "isstopTrade": false
    },
    {
      "LotNo": 1,
      "TradeNoOnThisLot": 44,
      "TradeTime": "22-02-2026 05:18:59",
      "asset": "1HZ25V",
      "action": "call",
      "moneyTrade": 1.0,
      "MoneyTradeType": "Fixed",
      "WinStatus": "loss",
      "Profit": -1.0,
      "BalanceOnLot": 0.7599999999999991,
      "winCon": "5",
      "lossCon": "10",
      "isstopTrade": false
    },
    {
      "LotNo": 1,
      "TradeNoOnThisLot": 45,
      "TradeTime": "22-02-2026 05:18:59",
      "asset": "1HZ10V",
      "action": "call",
      "moneyTrade": 1.0,
      "MoneyTradeType": "Fixed",
      "WinStatus": "win",
      "Profit": 0.95,
      "BalanceOnLot": 1.709999999999999,
      "winCon": "5",
      "lossCon": "10",
      "isstopTrade": false
    },
    {
      "LotNo": 1,
      "TradeNoOnThisLot": 46,
      "TradeTime": "22-02-2026 05:18:59",
      "asset": "1HZ75V",
      "action": "put",
      "moneyTrade": 1.0,
      "MoneyTradeType": "Fixed",
      "WinStatus": "win",
      "Profit": 0.94,
      "BalanceOnLot": 2.649999999999999,
      "winCon": "5",
      "lossCon": "10",
      "isstopTrade": false
    },
    {
      "LotNo": 1,
      "TradeNoOnThisLot": 47,
      "TradeTime": "22-02-2026 05:19:57",
      "asset": "1HZ10V",
      "action": "call",
      "moneyTrade": 1.0,
      "MoneyTradeType": "Fixed",
      "WinStatus": "loss",
      "Profit": -1.0,
      "BalanceOnLot": 1.649999999999999,
      "winCon": "5",
      "lossCon": "10",
      "isstopTrade": false
    },
    {
      "LotNo": 1,
      "TradeNoOnThisLot": 48,
      "TradeTime": "22-02-2026 05:19:58",
      "asset": "R_100",
      "action": "put",
      "moneyTrade": 1.0,
      "MoneyTradeType": "Fixed",
      "WinStatus": "win",
      "Profit": 0.94,
      "BalanceOnLot": 2.589999999999999,
      "winCon": "5",
      "lossCon": "10",
      "isstopTrade": false
    },
    {
      "LotNo": 1,
      "TradeNoOnThisLot": 49,
      "TradeTime": "22-02-2026 05:19:58",
      "asset": "1HZ25V",
      "action": "call",
      "moneyTrade": 1.0,
      "MoneyTradeType": "Fixed",
      "WinStatus": "win",
      "Profit": 0.95,
      "BalanceOnLot": 3.539999999999999,
      "winCon": "5",
      "lossCon": "10",
      "isstopTrade": false
    },
    {
      "LotNo": 1,
      "TradeNoOnThisLot": 50,
      "TradeTime": "22-02-2026 05:20:58",
      "asset": "1HZ10V",
      "action": "call",
      "moneyTrade": 1.0,
      "MoneyTradeType": "Fixed",
      "WinStatus": "loss",
      "Profit": -1.0,
      "BalanceOnLot": 2.539999999999999,
      "winCon": "5",
      "lossCon": "10",
      "isstopTrade": false
    },
    {
      "LotNo": 1,
      "TradeNoOnThisLot": 51,
      "TradeTime": "22-02-2026 05:20:59",
      "asset": "1HZ50V",
      "action": "put",
      "moneyTrade": 1.0,
      "MoneyTradeType": "Fixed",
      "WinStatus": "loss",
      "Profit": -1.0,
      "BalanceOnLot": 1.5399999999999991,
      "winCon": "5",
      "lossCon": "10",
      "isstopTrade": false
    },
    {
      "LotNo": 1,
      "TradeNoOnThisLot": 52,
      "TradeTime": "22-02-2026 05:20:59",
      "asset": "1HZ75V",
      "action": "put",
      "moneyTrade": 1.0,
      "MoneyTradeType": "Fixed",
      "WinStatus": "win",
      "Profit": 0.94,
      "BalanceOnLot": 2.479999999999999,
      "winCon": "5",
      "lossCon": "10",
      "isstopTrade": false
    },
    {
      "LotNo": 1,
      "TradeNoOnThisLot": 53,
      "TradeTime": "22-02-2026 05:20:59",
      "asset": "1HZ100V",
      "action": "put",
      "moneyTrade": 1.0,
      "MoneyTradeType": "Fixed",
      "WinStatus": "win",
      "Profit": 0.94,
      "BalanceOnLot": 3.419999999999999,
      "winCon": "5",
      "lossCon": "10",
      "isstopTrade": false
    },
    {
      "LotNo": 1,
      "TradeNoOnThisLot": 54,
      "TradeTime": "22-02-2026 05:21:02",
      "asset": "R_25",
      "action": "put",
      "moneyTrade": 1.0,
      "MoneyTradeType": "Fixed",
      "WinStatus": "loss",
      "Profit": -1.0,
      "BalanceOnLot": 2.419999999999999,
      "winCon": "5",
      "lossCon": "10",
      "isstopTrade": false
    }
  ]
}